{"is_source_file": true, "format": "JavaScript (React JSX)", "description": "React component for the Upload page, providing a placeholder UI with instructions for uploading files.", "external_files": ["react"], "external_methods": [], "published": ["Upload"], "classes": [], "methods": [{"name": "Upload()", "description": "React functional component rendering the upload placeholder UI.", "scope": "", "scopeKind": ""}], "calls": [], "search-terms": ["Upload", "React", "JSX", "upload page", "file upload UI", "placeholder"], "state": 2, "file_id": 16, "knowledge_revision": 33, "git_revision": "", "ctags": [{"_type": "tag", "name": "Upload", "path": "/home/kavia/workspace/code-generation/quoteextractor-platform-29-38/quote_extraction_frontend/src/pages/Upload.jsx", "pattern": "/^export default function Upload() {$/", "language": "JavaScript", "kind": "function", "signature": "()"}, {"_type": "tag", "name": "background", "path": "/home/kavia/workspace/code-generation/quoteextractor-platform-29-38/quote_extraction_frontend/src/pages/Upload.jsx", "pattern": "/^  background: \"var(--bg-secondary)\",$/", "language": "JavaScript", "kind": "property", "scope": "boxStyle", "scopeKind": "class"}, {"_type": "tag", "name": "border", "path": "/home/kavia/workspace/code-generation/quoteextractor-platform-29-38/quote_extraction_frontend/src/pages/Upload.jsx", "pattern": "/^  border: \"2px dashed var(--border-color)\",$/", "language": "JavaScript", "kind": "property", "scope": "boxStyle", "scopeKind": "class"}, {"_type": "tag", "name": "borderRadius", "path": "/home/kavia/workspace/code-generation/quoteextractor-platform-29-38/quote_extraction_frontend/src/pages/Upload.jsx", "pattern": "/^  borderRadius: 12,$/", "language": "JavaScript", "kind": "property", "scope": "boxStyle", "scopeKind": "class"}, {"_type": "tag", "name": "boxStyle", "path": "/home/kavia/workspace/code-generation/quoteextractor-platform-29-38/quote_extraction_frontend/src/pages/Upload.jsx", "pattern": "/^const boxStyle = {$/", "language": "JavaScript", "kind": "class"}, {"_type": "tag", "name": "color", "path": "/home/kavia/workspace/code-generation/quoteextractor-platform-29-38/quote_extraction_frontend/src/pages/Upload.jsx", "pattern": "/^  color: \"var(--text-primary)\",$/", "language": "JavaScript", "kind": "property", "scope": "boxStyle", "scopeKind": "class"}, {"_type": "tag", "name": "marginTop", "path": "/home/kavia/workspace/code-generation/quoteextractor-platform-29-38/quote_extraction_frontend/src/pages/Upload.jsx", "pattern": "/^  marginTop: 16,$/", "language": "JavaScript", "kind": "property", "scope": "boxStyle", "scopeKind": "class"}, {"_type": "tag", "name": "padding", "path": "/home/kavia/workspace/code-generation/quoteextractor-platform-29-38/quote_extraction_frontend/src/pages/Upload.jsx", "pattern": "/^  padding: 24,$/", "language": "JavaScript", "kind": "property", "scope": "boxStyle", "scopeKind": "class"}], "hash": "740c2ebda5f0ca28babc967aced961dc", "format-version": 4, "code-base-name": "quote_extraction_frontend", "filename": "quote_extraction_frontend/src/pages/Upload.jsx", "fields": [{"name": "background: \"var(--bg-secondary)\",", "scope": "boxStyle", "scopeKind": "class", "description": "unavailable"}, {"name": "border: \"2px dashed var(--border-color)\",", "scope": "boxStyle", "scopeKind": "class", "description": "unavailable"}, {"name": "borderRadius: 12,", "scope": "boxStyle", "scopeKind": "class", "description": "unavailable"}, {"name": "color: \"var(--text-primary)\",", "scope": "boxStyle", "scopeKind": "class", "description": "unavailable"}, {"name": "marginTop: 16,", "scope": "boxStyle", "scopeKind": "class", "description": "unavailable"}, {"name": "padding: 24,", "scope": "boxStyle", "scopeKind": "class", "description": "unavailable"}], "revision_history": [{"33": ""}]}